[
 {"id":"1","pregunta":"Who is Ebcad?","opc1":"<img class='img-thumbnail' src='img/2/01_1.png'>","opc2":"<img class='img-thumbnail' src='img/2/01_2.png'>","correcta":"1"},
 {"id":"2","pregunta":"This is a classroom.","opc1":"<img class='img-thumbnail' src='img/2/01_3.png'>","opc2":"<img class='img-thumbnail' src='img/2/01_4.png'>","correcta":"2"},
 {"id":"3","pregunta":"This is my school.","opc1":"<img class='img-thumbnail' src='img/2/01_5.png'>","opc2":"<img class='img-thumbnail' src='img/2/01_6.png'>","correcta":"1"},
 {"id":"4","pregunta":"I feel happy at school.","opc1":"<img class='img-thumbnail' src='img/2/01_7.png'>","opc2":"<img class='img-thumbnail' src='img/2/01_8.png'>","correcta":"1"}
 ]
